setup.py
worldofproxy/__init__.py
worldofproxy.egg-info/PKG-INFO
worldofproxy.egg-info/SOURCES.txt
worldofproxy.egg-info/dependency_links.txt
worldofproxy.egg-info/top_level.txt