Metadata-Version: 1.0
Name: worldofproxy
Version: 1.0.0
Summary: World of proxy python API
Home-page: http://bitbucket.org/zeus/worldofproxy
Author: Pavel Zhukov
Author-email: gelios@gmail.com
License: GPL
Keywords: proxies
Platform: UNKNOWN
